humble_get/__init__.py
humble_get/cli.py
humble_get/humble_get.py
humble_get-0.1.0.dist-info/LICENSE
humble_get-0.1.0.dist-info/METADATA
humble_get-0.1.0.dist-info/WHEEL
humble_get-0.1.0.dist-info/entry_points.txt
humble_get-0.1.0.dist-info/top_level.txt
humble_get-0.1.0.dist-info/RECORD
