Metadata-Version: 2.1
Name: humble-get
Version: 0.1.0
Summary: Humble-gs all of your books from Humblebundle order.
Home-page: https://github.com/bobrinik/humble_get
Author: humble-get
Author-email: bobrinik@pm.me
License: MIT license
Keywords: humble_get
Platform: UNKNOWN
Classifier: License :: OSI Approved :: MIT License
License-File: LICENSE
Requires-Dist: Click (>=6.0)
